Metadata-Version: 2.1
Name: pre-reco-utils
Version: 2021.2.17
Summary: Recommender System Utilities
Home-page: https://github.com/microsoft/recommenders
Author: RecoDev Team at Microsoft
Author-email: RecoDevTeam@service.microsoft.com
License: UNKNOWN
Keywords: recommendations recommenders recommender system engine machine learning python spark gpu
Platform: UNKNOWN
Classifier: Development Status :: 4 - Beta
Classifier: Intended Audience :: Developers
Classifier: Intended Audience :: Science/Research
Classifier: Topic :: Scientific/Engineering
Classifier: Topic :: Software Development :: Libraries :: Python Modules
Classifier: License :: OSI Approved :: MIT License
Classifier: Programming Language :: Python :: 3.6
Classifier: Programming Language :: Python :: 3.7
Classifier: Programming Language :: Python :: 3.8
Classifier: Programming Language :: Python :: 3.9
Requires-Python: >=3.6, <4
Provides-Extra: jupyter
Requires-Dist: azureml-sdk[notebooks] (==1.22.0) ; extra == 'jupyter'
Requires-Dist: ipykernel (>=4.6.1) ; extra == 'jupyter'
Requires-Dist: jupyter (>=1.0.0) ; extra == 'jupyter'
Requires-Dist: nbconvert (==6.0.7) ; extra == 'jupyter'
Provides-Extra: pytorch
Requires-Dist: pytorch (>=1.0.0) ; extra == 'pytorch'
Provides-Extra: required
Requires-Dist: flask (==1.1.1) ; extra == 'required'
Requires-Dist: requests ; extra == 'required'
Requires-Dist: pandas (==1.1.3) ; extra == 'required'
Requires-Dist: azureml-sdk (==1.22.0) ; extra == 'required'
Requires-Dist: azure-storage-blob (<12.8.0) ; extra == 'required'
Requires-Dist: azure-cli-core (==2.19.1) ; extra == 'required'
Requires-Dist: azure-mgmt-cosmosdb (==6.0.0) ; extra == 'required'
Requires-Dist: category-encoders (>=1.3.0) ; extra == 'required'
Requires-Dist: hyperopt (==0.2.5) ; extra == 'required'
Requires-Dist: idna ; extra == 'required'
Requires-Dist: locustio (==0.999) ; extra == 'required'
Requires-Dist: memory-profiler (>=0.54.0) ; extra == 'required'
Requires-Dist: pydocumentdb (>=2.3.3) ; extra == 'required'
Requires-Dist: pymanopt (==0.2.5) ; extra == 'required'
Requires-Dist: xlearn (==0.40a1) ; extra == 'required'
Requires-Dist: transformers (==4.3.2) ; extra == 'required'
Requires-Dist: bottleneck (==1.2.1) ; extra == 'required'
Requires-Dist: dask (>=0.17.1) ; extra == 'required'
Requires-Dist: fastparquet (>=0.1.6) ; extra == 'required'
Requires-Dist: lightfm (==1.15) ; extra == 'required'
Requires-Dist: matplotlib (>=2.2.2) ; extra == 'required'
Requires-Dist: nltk (>=3.4) ; extra == 'required'
Requires-Dist: numpy (>=1.13.3) ; extra == 'required'
Requires-Dist: seaborn (>=0.8.1) ; extra == 'required'
Requires-Dist: scikit-learn (>=0.19.1) ; extra == 'required'
Requires-Dist: scipy (>=1.0.0) ; extra == 'required'
Requires-Dist: scikit-surprise (>=1.0.6) ; extra == 'required'
Requires-Dist: swig (==3.0.12) ; extra == 'required'
Requires-Dist: lightgbm (<3.0,>=2.2.1) ; extra == 'required'
Requires-Dist: cornac (>=1.1.2) ; extra == 'required'
Requires-Dist: tqdm (>=4.31.1) ; extra == 'required'
Requires-Dist: dataclasses (>=0.6) ; (python_version < "3.7") and extra == 'required'
Provides-Extra: tensorflow
Requires-Dist: azureml-sdk[notebooks,tensorboard] (==1.22.0) ; extra == 'tensorflow'
Requires-Dist: tensorflow (==1.15.4) ; extra == 'tensorflow'
Provides-Extra: test
Requires-Dist: black (>=18.6b4) ; extra == 'test'
Requires-Dist: mock (==2.0.0) ; extra == 'test'
Requires-Dist: papermill (>=2.2.0) ; extra == 'test'
Requires-Dist: scrapbook (>=0.5.0) ; extra == 'test'
